colav_unsafe_set/__init__.py
colav_unsafe_set/collision_geometry/__init__.py
colav_unsafe_set/collision_geometry/collision_geometry.py
colav_unsafe_set/indices_of_interest/__init__.py
colav_unsafe_set/indices_of_interest/indices_of_interest.py
colav_unsafe_set/indices_of_interest/unionise_indices_of_interest.py
colav_unsafe_set/objects/__init__.py
colav_unsafe_set/objects/objects.py
colav_unsafe_set/position_prediction/__init__.py
colav_unsafe_set/position_prediction/position_prediction.py
colav_unsafe_set/risk_assessment/__init__.py
colav_unsafe_set/risk_assessment/obstacle_metric_calculator.py
colav_unsafe_set/risk_assessment/risk_assessment.py
colav_unsafe_set/unsafe_set/__init__.py
colav_unsafe_set/unsafe_set/unsafe_set.py
colav_unsafe_set-0.0.4.dist-info/METADATA
colav_unsafe_set-0.0.4.dist-info/WHEEL
colav_unsafe_set-0.0.4.dist-info/licenses/LICENSE
colav_unsafe_set-0.0.4.dist-info/RECORD
