Metadata-Version: 2.4
Name: colav-unsafe-set
Version: 0.0.4
Summary: A Python library for generating unsafe sets utilising the Indices of Interest.
Project-URL: Documentation, https://github.com/RyanMcKeeQUB/colav-unsafe-set/blob/main/README.md
Project-URL: Issues, https://github.com/RyanMcKeeQUB/colav-unsafe-set/issues
Project-URL: Source, https://github.com/RyanMcKeeQUB/colav-unsafe-set
Author-email: Ryan McKee <r.mckee@qub.ac.uk>
License: MIT License
License-File: LICENSE
Classifier: Development Status :: 4 - Beta
Classifier: Programming Language :: Python
Classifier: Programming Language :: Python :: 3.8
Classifier: Programming Language :: Python :: 3.9
Classifier: Programming Language :: Python :: 3.10
Classifier: Programming Language :: Python :: 3.11
Classifier: Programming Language :: Python :: 3.12
Classifier: Programming Language :: Python :: Implementation :: CPython
Classifier: Programming Language :: Python :: Implementation :: PyPy
Requires-Dist: hatch
Requires-Dist: lark
Requires-Dist: matplotlib
Requires-Dist: pandas
Requires-Dist: protobuf<=3.20.1
Requires-Dist: pyyaml
Requires-Dist: scipy
